autogl/__init__.py
autogl/backend/__init__.py
autogl/backend/_dependent_backend.py
autogl/data/__init__.py
autogl/data/data.py
autogl/data/download.py
autogl/data/extract.py
autogl/data/makedirs.py
autogl/data/_dataset/__init__.py
autogl/data/_dataset/_dataset.py
autogl/data/_dataset/_in_memory_static_graph_set.py
autogl/data/graph/__init__.py
autogl/data/graph/_general_static_graph/__init__.py
autogl/data/graph/_general_static_graph/_abstract_views.py
autogl/data/graph/_general_static_graph/_canonical_edge_type.py
autogl/data/graph/_general_static_graph/_general_static_graph.py
autogl/data/graph/_general_static_graph/_general_static_graph_default_implementation.py
autogl/data/graph/_general_static_graph/_general_static_graph_dgl_implementation.py
autogl/data/graph/_general_static_graph/_general_static_graph_generator.py
autogl/data/graph/_general_static_graph/utils/__init__.py
autogl/data/graph/_general_static_graph/utils/conversion/__init__.py
autogl/data/graph/_general_static_graph/utils/conversion/_dgl.py
autogl/data/graph/_general_static_graph/utils/conversion/_general.py
autogl/data/graph/_general_static_graph/utils/conversion/_nx.py
autogl/data/graph/_general_static_graph/utils/conversion/_pyg.py
autogl/data/graph/utils/__init__.py
autogl/data/graph/utils/conversion.py
autogl/datasets/__init__.py
autogl/datasets/_data_source.py
autogl/datasets/_dataset_registry.py
autogl/datasets/_dgl.py
autogl/datasets/_gtn_data.py
autogl/datasets/_matlab_matrix.py
autogl/datasets/_ogb.py
autogl/datasets/_pyg.py
autogl/datasets/_heterogeneous_datasets/__init__.py
autogl/datasets/_heterogeneous_datasets/_dgl_heterogeneous_datasets.py
autogl/datasets/utils/__init__.py
autogl/datasets/utils/_general.py
autogl/datasets/utils/_pyg.py
autogl/datasets/utils/_split_edges/__init__.py
autogl/datasets/utils/_split_edges/_dgl_compatible.py
autogl/datasets/utils/_split_edges/_pyg_compatible.py
autogl/datasets/utils/_split_edges/split_edges.py
autogl-0.4.0.dist-info/LICENSE
autogl-0.4.0.dist-info/METADATA
autogl-0.4.0.dist-info/WHEEL
autogl-0.4.0.dist-info/top_level.txt
autogl-0.4.0.dist-info/RECORD
