Metadata-Version: 2.1
Name: autogl
Version: 0.4.0
Summary: AutoML tools for graph-structure dataset
Author: THUMNLab/aglteam
Author-email: autogl@tsinghua.edu.cn
Maintainer: THUMNLab/aglteam
Classifier: Development Status :: 4 - Beta
Classifier: License :: OSI Approved :: Apache Software License
Classifier: Programming Language :: Python :: 3 :: Only
Classifier: Programming Language :: Python :: 3.6
Requires-Python: ~=3.6
License-File: LICENSE
Requires-Dist: bayesian-optimization
Requires-Dist: chocolate
Requires-Dist: dill
Requires-Dist: deeprobust
Requires-Dist: hyperopt
Requires-Dist: lightgbm
Requires-Dist: networkx
Requires-Dist: numpy
Requires-Dist: numba
Requires-Dist: netlsd
Requires-Dist: ogb
Requires-Dist: psutil
Requires-Dist: pyyaml
Requires-Dist: requests
Requires-Dist: scikit-learn
Requires-Dist: scipy
Requires-Dist: tabulate
Requires-Dist: tqdm
Requires-Dist: nni (==2.8)
